[
  {
    "title": "First query",
    "file": "first.sql",
    "args": [
      {
        "name": "ssn (number)",
        "type": "str"
      },
      {
        "name": "year",
        "type": "str"
      }
    ]
  },
  {
    "title": "Second query",
    "file": "second.sql",
    "args": [
      {
        "name" : "year",
        "type" : "str"
      }
    ]
  },
  {
    "title": "Third query",
    "file": "third.sql",
    "args": [
      {
        "name": "year (number)",
        "type": "str"
      },
      {
        "name": "month (number)",
        "type": "str"
      }
    ]
  },
  {
    "title": "Fourth query",
    "file": "fourth.sql",
    "args": [
      {
        "name": "year (number)",
        "type": "str"
      },
      {
        "name": "month (number)",
        "type": "str"
      }
    ]
  },
  {
    "title": "Fifth query",
    "file": "fifth.sql",
    "args": [
      {
        "name": "year",
        "type": "str"
      }
    ]
  }
]